takopi_matrix/__init__.py
takopi_matrix/backend.py
takopi_matrix/crypto.py
takopi_matrix/engine_defaults.py
takopi_matrix/files.py
takopi_matrix/markdown.py
takopi_matrix/render.py
takopi_matrix/room_prefs.py
takopi_matrix/room_projects.py
takopi_matrix/state_store.py
takopi_matrix/types.py
takopi_matrix/bridge/__init__.py
takopi_matrix/bridge/cancel.py
takopi_matrix/bridge/commands.py
takopi_matrix/bridge/config.py
takopi_matrix/bridge/events.py
takopi_matrix/bridge/presenter.py
takopi_matrix/bridge/runtime.py
takopi_matrix/bridge/transcription.py
takopi_matrix/bridge/transport.py
takopi_matrix/client/__init__.py
takopi_matrix/client/client.py
takopi_matrix/client/content_builders.py
takopi_matrix/client/outbox.py
takopi_matrix/client/parsers.py
takopi_matrix/client/protocol.py
takopi_matrix/onboarding/__init__.py
takopi_matrix/onboarding/config_gen.py
takopi_matrix/onboarding/discovery.py
takopi_matrix/onboarding/rooms.py
takopi_matrix/onboarding/ui.py
takopi_matrix/onboarding/validation.py
takopi_matrix/onboarding/wizard.py
takopi_matrix-0.2.0.dist-info/METADATA
takopi_matrix-0.2.0.dist-info/WHEEL
takopi_matrix-0.2.0.dist-info/entry_points.txt
takopi_matrix-0.2.0.dist-info/licenses/LICENSE
takopi_matrix-0.2.0.dist-info/RECORD
