Metadata-Version: 2.4
Name: takopi-matrix
Version: 0.2.0
Summary: Matrix transport backend for Takopi
Project-URL: Homepage, https://github.com/Zorro909/takopi-matrix
Project-URL: Repository, https://github.com/Zorro909/takopi-matrix
Project-URL: Issues, https://github.com/Zorro909/takopi-matrix/issues
License: MIT License
License-File: LICENSE
Classifier: License :: OSI Approved :: MIT License
Classifier: Operating System :: OS Independent
Classifier: Programming Language :: Python :: 3
Classifier: Programming Language :: Python :: 3 :: Only
Classifier: Programming Language :: Python :: 3.14
Requires-Python: >=3.14
Requires-Dist: anyio>=4.12.0
Requires-Dist: httpx>=0.28.1
Requires-Dist: markdown-it-py
Requires-Dist: matrix-nio[e2e]>=0.24
Requires-Dist: pydantic-settings>=2.12.0
Requires-Dist: pydantic>=2.12.5
Requires-Dist: questionary>=2.1.1
Requires-Dist: rich>=14.2.0
Requires-Dist: structlog>=25.5.0
Requires-Dist: takopi>=0.20.0
Requires-Dist: tomli-w>=1.2.0
Requires-Dist: tomlkit>=0.13.0
